Assignment-5/Q4/D ff/d_ff.v
module d_ff(d, clk, reset, q, qbar);

input d, clk, reset;
output reg q=0, qbar = 1;

always @ (posedge clk) begin

    if(reset == 1) q = 0;
    else q = d;
    
    qbar = ~q;
end
endmodule

Assignment-5/Q4/D ff/d_tb.v
`include "d_ff.v"

module d_tb;
    reg d, clk, reset;
    wire q, qbar;

    d_ff inst0(d, clk, reset, q, qbar);

   
initial begin
$monitor("T=%t | CLK = %b | D = %b | reset = %b | Q = %b | QBAR = %b", $time, clk, d, reset, q, qbar);
$dumpfile("d_dump.vcd");
$dumpvars(0, d_tb);
end 

    initial begin
        reset = 1; d = 1'b1; clk = 0;
        #1 clk = 1;
        #1 clk = 0; d = 1'b0;
        #1 clk = 1;
        #1 reset = 0; clk = 0;
        #1 clk = 1; d = 1'b1;
        #1 clk = 0; d = 1'b0;
        #1 clk = 1;
        #1 clk = 0; d = 1'b1;
        #1 clk = 1;
    end
endmodule

Assignment-5/Q4/D ff/d_dump.vcd
$date
	Fri Mar 18 13:10:16 2022
$end
$version
	Icarus Verilog
$end
$timescale
	1s
$end
$scope module d_tb $end
$var wire 1 ! q $end
$var wire 1 " qbar $end
$var reg 1 # clk $end
$var reg 1 $ d $end
$var reg 1 % reset $end
$scope module inst0 $end
$var wire 1 & clk $end
$var wire 1 ' d $end
$var wire 1 ( reset $end
$var reg 1 ) q $end
$var reg 1 * qbar $end
$upscope $end
$upscope $end
$enddefinitions $end
#0
$dumpvars
1*
0)
1(
1'
0&
1%
1$
0#
1"
0!
$end
#1
1#
1&
#2
0$
0'
0#
0&
#3
1#
1&
#4
0#
0&
0%
0(
#5
0*
0"
1)
1!
1$
1'
1#
1&
#6
0$
0'
0#
0&
#7
1*
1"
0)
0!
1#
1&
#8
1$
1'
0#
0&
#9
0*
0"
1)
1!
1#
1&
