Assignment-5/Q1/MUX4x1.v
module MUX4x1(output reg Y, input a, b, c, d, s0, s1);
    
    always @ (*)
    begin
        if(s1 == 1'b0 & s0 == 1'b0) Y <= a;
        else if(s1 == 1'b0 & s0 == 1'b1) Y <= b;
        else if(s1 == 1'b1 & s0 == 1'b0) Y <= c;
        else if(s1 == 1'b1 & s0 == 1'b1) Y <= d;
    end

endmodule

Assignment-5/Q1/q1_tb.v
`include "MUX4x1.v"
module q3_tb;

wire Y;
reg a, b, c, d, s0, s1;

MUX4x1 inst0(Y, a, b, c, d, s0, s1);

initial begin

$monitor("T=%t | a=%b | b=%b | c=%b | d=%b | s0=%b | s1=%b | Y=%b", $time, a, b, c, d, s0, s1, Y);
$dumpfile("q1_dump.vcd");
$dumpvars();
end

initial begin
a = 1'b1; b = 1'b0; c = 1'b1; d = 1'b1; s0 = 1'b0; s1 = 1'b1;
#1 a = 1'b0; b = 1'b1; c = 1'b0; d = 1'b0; s0 = 1'b0; s1 = 1'b1;
#1 a = 1'b0; b = 1'b0; c = 1'b1; d = 1'b0; s0 = 1'b1; s1 = 1'b0;
#1 a = 1'b0; b = 1'b0; c = 1'b0; d = 1'b1; s0 = 1'b1; s1 = 1'b1;
#1 a = 1'b1; b = 1'b0; c = 1'b0; d = 1'b0; s0 = 1'b0; s1 = 1'b0;
#1 a = 1'b1; b = 1'b0; c = 1'b1; d = 1'b0; s0 = 1'b0; s1 = 1'b1;
#1 a = 1'b1; b = 1'b1; c = 1'b0; d = 1'b0; s0 = 1'b0; s1 = 1'b1;
#1 a = 1'b0; b = 1'b1; c = 1'b0; d = 1'b1; s0 = 1'b1; s1 = 1'b0;
#1 a = 1'b0; b = 1'b0; c = 1'b1; d = 1'b0; s0 = 1'b1; s1 = 1'b0;
#1 a = 1'b1; b = 1'b0; c = 1'b1; d = 1'b0; s0 = 1'b1; s1 = 1'b1;
#1 a = 1'b1; b = 1'b1; c = 1'b0; d = 1'b1; s0 = 1'b0; s1 = 1'b1;
end
endmodule

Assignment-5/Q1/q1_dump.vcd
$date
	Fri Mar 11 10:35:11 2022
$end
$version
	Icarus Verilog
$end
$timescale
	1s
$end
$scope module q3_tb $end
$var wire 1 ! Y $end
$var reg 1 " a $end
$var reg 1 # b $end
$var reg 1 $ c $end
$var reg 1 % d $end
$var reg 1 & s0 $end
$var reg 1 ' s1 $end
$scope module inst0 $end
$var wire 1 ( a $end
$var wire 1 ) b $end
$var wire 1 * c $end
$var wire 1 + d $end
$var wire 1 , s0 $end
$var wire 1 - s1 $end
$var reg 1 . Y $end
$upscope $end
$upscope $end
$enddefinitions $end
#0
$dumpvars
1.
1-
0,
1+
1*
0)
1(
1'
0&
1%
1$
0#
1"
1!
$end
#1
0.
0!
0%
0+
0$
0*
1#
1)
0"
0(
#2
0'
0-
1&
1,
1$
1*
0#
0)
#3
1.
1!
1'
1-
1%
1+
0$
0*
#4
0'
0-
0&
0,
0%
0+
1"
1(
#5
1'
1-
1$
1*
#6
0.
0!
0$
0*
1#
1)
#7
1.
1!
0'
0-
1&
1,
1%
1+
0"
0(
#8
0.
0!
0%
0+
1$
1*
0#
0)
#9
1'
1-
1"
1(
#10
0&
0,
1%
1+
0$
0*
1#
1)
