Assignment-5/Q4/Master slave FF/ms_ff.v
// First module is a D Flip Flop
module d_ff(q, qbar, clk, reset, d);

input d, clk, reset;
output reg q=0, qbar = 1;

always @ (posedge clk) begin

    if(reset == 1) q = 0;
    else q = d;
    
    qbar = ~q;
end
endmodule

module ms_ff(q, qbar, clk, rst, d);
	output q;
	output qbar;
	input clk, rst;
	input d;

	wire clk_bar, q1, q1bar; // inverted clock and intermediate q output of Master

	assign clk_bar = ~clk;
	assign qbar = ~q;

// master slave operation
	d_ff msf0(q1, q1bar, clk, rst, d);
	d_ff msf1(q, qbar, clk_bar, rst, q1);

endmodule

Assignment-5/Q4/Master slave FF/ms_tb.v
`include "ms_ff.v"

module ms_tb;
    reg d, clk, reset;
    wire q, qbar;

    ms_ff inst0(q, qbar, clk, reset, d);

   
initial begin
$monitor("T=%t | CLK = %b | D = %b | reset = %b | Q = %b | QBAR = %b", $time, clk, d, reset, q, qbar);
$dumpfile("ms_dump.vcd");
$dumpvars(0, ms_tb);
end 

    initial begin
        reset = 1; d = 1'b1; clk = 0;
        #1 clk = 1;
        #1 clk = 0; d = 1'b0;
        #1 clk = 1;
        #1 reset = 0; clk = 0;
        #1 clk = 1; d = 1'b1;
        #1 clk = 0; d = 1'b0;
        #1 clk = 1;
        #1 clk = 0; d = 1'b1;
        #1 clk = 1;
    end
endmodule

Assignment-5/Q4/Master slave FF/ms_dump.vcd
$date
	Fri Mar 18 21:53:09 2022
$end
$version
	Icarus Verilog
$end
$timescale
	1s
$end
$scope module ms_tb $end
$var wire 1 ! q $end
$var wire 1 " qbar $end
$var reg 1 # clk $end
$var reg 1 $ d $end
$var reg 1 % reset $end
$scope module inst0 $end
$var wire 1 & clk $end
$var wire 1 ' clk_bar $end
$var wire 1 ( d $end
$var wire 1 ! q $end
$var wire 1 ) q1 $end
$var wire 1 * q1bar $end
$var wire 1 " qbar $end
$var wire 1 + rst $end
$scope module msf0 $end
$var wire 1 & clk $end
$var wire 1 ( d $end
$var wire 1 + reset $end
$var reg 1 , q $end
$var reg 1 - qbar $end
$upscope $end
$scope module msf1 $end
$var wire 1 ' clk $end
$var wire 1 ) d $end
$var wire 1 + reset $end
$var reg 1 . q $end
$var reg 1 / qbar $end
$upscope $end
$upscope $end
$upscope $end
$enddefinitions $end
#0
$dumpvars
1/
0.
1-
0,
1+
1*
0)
1(
1'
0&
1%
1$
0#
1"
0!
$end
#1
0'
1#
1&
#2
1'
0$
0(
0#
0&
#3
0'
1#
1&
#4
1'
0#
0&
0%
0+
#5
0'
0-
0*
1,
1)
1$
1(
1#
1&
#6
0/
0"
1.
1!
1'
0$
0(
0#
0&
#7
0'
1-
1*
0,
0)
1#
1&
#8
1/
1"
0.
0!
1'
1$
1(
0#
0&
#9
0'
0-
0*
1,
1)
1#
1&
