Assignment-5/Q5/pipo.v
module pipo(out, in, clk, reset); //positive edge triggered PIPO register
input[3:0] in;
input clk, reset;
output reg[3:0] out;

    always @(posedge clk) begin
        if(reset) out = 4'b 0000;
        else out = in;
    end
endmodule

Assignment-5/Q5/q5_tb.v
`include "pipo.v"

module q5_tb;
    reg CLK, clr;
    reg [3:0] in;
    wire [3:0] out;
    integer k;

    pipo PIPO(out,in,CLK, clr);

    initial begin
        $monitor("%t| CLK = %b | Reset=%b | Input = %4b | Output = %4b", $time, CLK, clr, in, out);
        $dumpfile("q5_dump.vcd");
        $dumpvars(0,q5_tb);
    end

    initial begin
        CLK=0; in=4'b0000; clr=0;
        #1 CLK=1;
        #1 CLK=0;clr =1;
        #1 CLK=1; in=4'b0001;
        #1 CLK=0;
        #1 CLK=1; clr = 0;
        #1 CLK=0; in=4'b0010;
        #1 CLK=1;
        #1 CLK=0; clr = 1;
        #1 CLK=1; in=4'b0100; clr = 0;
        #1 CLK=0;clr = 1;
        #1 CLK=1; in=4'b1001;
        #1 CLK=0; clr = 0;
        #1 CLK=1;
        #1 CLK=0; in=4'b1111;
        #1;
    end
endmodule

Assignment-5/Q5/Question5.vcd
$date
	Fri Mar 18 13:38:52 2022
$end
$version
	Icarus Verilog
$end
$timescale
	1s
$end
$scope module q5_tb $end
$var wire 4 ! out [3:0] $end
$var reg 1 " CLK $end
$var reg 1 # clr $end
$var reg 4 $ in [3:0] $end
$scope module PIPO $end
$var wire 1 % clk $end
$var wire 4 & in [3:0] $end
$var wire 1 ' reset $end
$var reg 4 ( out [3:0] $end
$upscope $end
$upscope $end
$enddefinitions $end
#0
$dumpvars
bx (
0'
b0 &
0%
b0 $
0#
0"
bx !
$end
#1
b0 (
b0 !
1"
1%
#2
0"
0%
#3
b1 (
b1 !
b1 $
b1 &
1"
1%
#4
0"
0%
#5
1"
1%
#6
b10 $
b10 &
0"
0%
#7
b10 (
b10 !
1"
1%
#8
0"
0%
#9
b100 (
b100 !
b100 $
b100 &
1"
1%
#10
0"
0%
#11
b1001 (
b1001 !
b1001 $
b1001 &
1"
1%
#12
0"
0%
#13
1"
1%
#14
b1111 $
b1111 &
0"
0%
